{
  "id": "tools",
  "type": "SharedSlice",
  "name": "Tools",
  "description": "Tools",
  "variations": [
    {
      "id": "default",
      "name": "Default",
      "docURL": "...",
      "version": "sktwi1xtmkfgx8626",
      "description": "Tools",
      "primary": {
        "title": {
          "type": "StructuredText",
          "config": {
            "label": "Title",
            "placeholder": "",
            "allowTargetBlank": true,
            "single": "heading2"
          }
        },
        "description": {
          "type": "StructuredText",
          "config": {
            "label": "Description",
            "placeholder": "",
            "allowTargetBlank": true,
            "single": "paragraph,strong,em,hyperlink"
          }
        },
        "primaryLink": {
          "config": {
            "label": "Primary Link",
            "placeholder": "",
            "select": null,
            "allowTargetBlank": true
          },
          "type": "Link"
        },
        "primaryLinkLabel": {
          "config": {
            "label": "Primary Link Label",
            "placeholder": ""
          },
          "type": "Text"
        },
        "secondaryLink": {
          "config": {
            "label": "Secondary Link",
            "placeholder": "",
            "select": null,
            "allowTargetBlank": true
          },
          "type": "Link"
        },
        "secondaryLinkLabel": {
          "config": {
            "label": "Secondary Link Label",
            "placeholder": ""
          },
          "type": "Text"
        }
      },
      "items": {
        "logo": {
          "config": {
            "label": "Logo",
            "constraint": {},
            "thumbnails": []
          },
          "type": "Image"
        },
        "logoDark": {
          "type": "Image",
          "config": {
            "label": "Logo Dark",
            "constraint": {},
            "thumbnails": []
          }
        }
      },
      "imageUrl": "https://images.prismic.io/slice-machine/621a5ec4-0387-4bc5-9860-2dd46cbc07cd_default_ss.png?auto=compress,format"
    }
  ]
}
